{
	"configurations" : 
	[
		{
			"directories" : 
			[
				{
					"build" : ".",
					"jsonFile" : "directory-.-Debug-d0094a50bb2071803777.json",
					"minimumCMakeVersion" : 
					{
						"string" : "3.23"
					},
					"projectIndex" : 0,
					"source" : ".",
					"targetIndexes" : 
					[
						0
					]
				}
			],
			"name" : "Debug",
			"projects" : 
			[
				{
					"directoryIndexes" : 
					[
						0
					],
					"name" : "E__Base_Converssion_",
					"targetIndexes" : 
					[
						0
					]
				}
			],
			"targets" : 
			[
				{
					"directoryIndex" : 0,
					"id" : "E__Base_Converssion_::@6890427a1f51a3e7e1df",
					"jsonFile" : "target-E__Base_Converssion_-Debug-f7b4f038b077fbb938de.json",
					"name" : "E__Base_Converssion_",
					"projectIndex" : 0
				}
			]
		}
	],
	"kind" : "codemodel",
	"paths" : 
	{
		"build" : "D:/problem solving/level1/E. Base Converssion/cmake-build-debug",
		"source" : "D:/problem solving/level1/E. Base Converssion"
	},
	"version" : 
	{
		"major" : 2,
		"minor" : 4
	}
}
